mseep_ramp_mcp-0.0.5.dist-info/licenses/LICENSE.txt
ramp_mcp/__init__.py
ramp_mcp/__main__.py
ramp_mcp/client.py
ramp_mcp/constants.py
ramp_mcp/memory_db.py
ramp_mcp/tools.py
ramp_mcp/types.py
ramp_mcp/utils.py
mseep_ramp_mcp-0.0.5.dist-info/METADATA
mseep_ramp_mcp-0.0.5.dist-info/WHEEL
mseep_ramp_mcp-0.0.5.dist-info/entry_points.txt
mseep_ramp_mcp-0.0.5.dist-info/top_level.txt
mseep_ramp_mcp-0.0.5.dist-info/RECORD
